anitui/__init__.py
anitui/browse.py
anitui/script/README.md
anitui/script/package-lock.json
anitui/script/package.json
anitui/script/run.sh
anitui/script/src/api/anilist.js
anitui/script/src/api/auth/auth_url.js
anitui/script/src/api/auth/gen_token.js
anitui/script/src/rpc.js
anitui/script/src/tests/parser.test.js
anitui/script/src/utils/config.js
anitui/script/src/utils/icon.js
anitui/script/src/utils/logger.js
anitui/script/src/utils/title_parser.js
anitui/script/src/vlc.js
anitui/utils/__init__.py
anitui/utils/anilist.py
anitui/utils/config.py
anitui/utils/parser.py
anitui/utils/size.py
anitui/widgets/__init__.py
anitui/widgets/header.py
anitui/widgets/progress.py
anitui/widgets/table.py
anitui-0.1.4.dist-info/entry_points.txt
anitui-0.1.4.dist-info/LICENSE
anitui-0.1.4.dist-info/WHEEL
anitui-0.1.4.dist-info/METADATA
anitui-0.1.4.dist-info/RECORD
